AUTHORS
COPYING
MANIFEST.in
README.rst
setup.cfg
setup.py
conf/base.conf
conf/example.conf
doc/README.rst
doc/conf.py
doc/index.rst
eyefi/__init__.py
eyefi/actions.py
eyefi/config.py
eyefi/exif_gps.py
eyefi/google_loc.py
eyefi/maclog.py
eyefi/server.py
eyefi/twisted_flickrapi.py
eyefi/viewer.py
eyefi.egg-info/PKG-INFO
eyefi.egg-info/SOURCES.txt
eyefi.egg-info/dependency_links.txt
eyefi.egg-info/entry_points.txt
eyefi.egg-info/namespace_packages.txt
eyefi.egg-info/requires.txt
eyefi.egg-info/top_level.txt
init/eyefi
tests/__init__.py
twisted/__init__.py
twisted/plugins/__init__.py
twisted/plugins/eyefi_plugin.py